MANIFEST.in
README.rst
setup.py
subtitlematcher/__init__.py
subtitlematcher/__main__.py
subtitlematcher.egg-info/PKG-INFO
subtitlematcher.egg-info/SOURCES.txt
subtitlematcher.egg-info/dependency_links.txt
subtitlematcher.egg-info/entry_points.txt
subtitlematcher.egg-info/not-zip-safe
subtitlematcher.egg-info/requires.txt
subtitlematcher.egg-info/top_level.txt