Metadata-Version: 1.0
Name: subtitlematcher
Version: 0.0.4
Summary: Matching videos and subtitles file names
Home-page: http://github.com/itsjef/subtitlematcher.git
Author: Duc Anh Tran
Author-email: td.anh0812@gmail.com
License: MIT
Platform: UNKNOWN
